{"_type":"export","__export_format":4,"__export_date":"2022-04-03T16:00:02.129Z","__export_source":"insomnia.desktop.app:v2022.2.1","resources":[{"_id":"req_ec688c22ea0f4cabbb32c8f31c80886d","parentId":"fld_9bb92b2a966641d782c611a5499ac983","modified":1648801460040,"created":1647601083584,"url":"{{ _.endpoint }}/api/nodes.php","name":"Liste des noeuds","description":"","method":"GET","body":{"mimeType":"application/x-www-form-urlencoded","params":[]},"parameters":[{"id":"pair_fefe6c657eab4b429e71eb4b797040eb","name":"id","value":"1","description":"","disabled":false}],"headers":[{"name":"Content-Type","value":"application/x-www-form-urlencoded","id":"pair_34f44f0a81ac464fb31489c5c74a977a"}],"authentication":{},"metaSortKey":-1647601083584,"isPrivate":false,"settingStoreCookies":true,"settingSendCookies":true,"settingDisableRenderRequestBody":false,"settingEncodeUrl":true,"settingRebuildPath":true,"settingFollowRedirects":"global","_type":"request"},{"_id":"fld_9bb92b2a966641d782c611a5499ac983","parentId":"wrk_6960ae46e9804ac3853867f836617bac","modified":1647601035317,"created":1647601025902,"name":"api/nodes.php","description":"","environment":{},"environmentPropertyOrder":null,"metaSortKey":-1647601025902,"_type":"request_group"},{"_id":"wrk_6960ae46e9804ac3853867f836617bac","parentId":null,"modified":1646381270592,"created":1646381270592,"name":"Monitoring Pesquiers","description":"","scope":"collection","_type":"workspace"},{"_id":"req_1c7fdecb75f64393aaa1995de339be4a","parentId":"fld_9bb92b2a966641d782c611a5499ac983","modified":1648118475250,"created":1647605629159,"url":"{{ _.endpoint }}/api/nodes.php","name":"Ajouter un noeud","description":"","method":"POST","body":{"mimeType":"application/json","text":"{\n\t\"name\": \"TestNomBalise1\",\n\t\"latitude\": \"43.0632\",\n\t\"longitude\": \"6.13975\",\n\t\"sensors_id\": \"1\"\n}"},"parameters":[],"headers":[{"name":"Content-Type","value":"application/json","id":"pair_bda73af8f66346cb86ab2d8f2e73ea51"}],"authentication":{},"metaSortKey":-1644188276117.625,"isPrivate":false,"settingStoreCookies":true,"settingSendCookies":true,"settingDisableRenderRequestBody":false,"settingEncodeUrl":true,"settingRebuildPath":true,"settingFollowRedirects":"global","_type":"request"},{"_id":"req_6d95e598b9824a81a0ccbeaaa43f920b","parentId":"fld_3c710cdd0bef447ba250465d99e8ce5e","modified":1648207435972,"created":1648207413350,"url":"{{ _.endpoint }}/api/sensors.php","name":"Liste des capteurs","description":"","method":"GET","body":{},"parameters":[],"headers":[],"authentication":{},"metaSortKey":-1647601083584,"isPrivate":false,"settingStoreCookies":true,"settingSendCookies":true,"settingDisableRenderRequestBody":false,"settingEncodeUrl":true,"settingRebuildPath":true,"settingFollowRedirects":"global","_type":"request"},{"_id":"fld_3c710cdd0bef447ba250465d99e8ce5e","parentId":"wrk_6960ae46e9804ac3853867f836617bac","modified":1648207413341,"created":1648207413341,"name":"api/sensors.php","description":"","environment":{},"environmentPropertyOrder":null,"metaSortKey":-1647600817579.25,"_type":"request_group"},{"_id":"req_b5ef0ad25ddd4c9cbc2e0469c94bb81c","parentId":"fld_3c710cdd0bef447ba250465d99e8ce5e","modified":1648207713618,"created":1648207413356,"url":"{{ _.endpoint }}/api/sensors.php","name":"Ajouter un capteurs","description":"","method":"POST","body":{"mimeType":"application/json","text":"{\n\t\"name\": \"temepr\",\n\t\"unite\": \"ts\",\n\t\"symbole\": \"te\"\n}"},"parameters":[],"headers":[{"name":"Content-Type","value":"application/json","id":"pair_bda73af8f66346cb86ab2d8f2e73ea51"}],"authentication":{},"metaSortKey":-1644188276117.625,"isPrivate":false,"settingStoreCookies":true,"settingSendCookies":true,"settingDisableRenderRequestBody":false,"settingEncodeUrl":true,"settingRebuildPath":true,"settingFollowRedirects":"global","_type":"request"},{"_id":"req_b1e7424cfa8f48268370c1799df93243","parentId":"fld_a80d9ace53414c208c113fc52a4544f4","modified":1647614634125,"created":1647605629154,"url":"{{ _.endpoint }}/api/alerts.php","name":"Lister les alertes","description":"","method":"GET","body":{},"parameters":[],"headers":[],"authentication":{},"metaSortKey":-1647601083584,"isPrivate":false,"settingStoreCookies":true,"settingSendCookies":true,"settingDisableRenderRequestBody":false,"settingEncodeUrl":true,"settingRebuildPath":true,"settingFollowRedirects":"global","_type":"request"},{"_id":"fld_a80d9ace53414c208c113fc52a4544f4","parentId":"wrk_6960ae46e9804ac3853867f836617bac","modified":1647605629150,"created":1647605629150,"name":"api/alerts.php","description":"","environment":{},"environmentPropertyOrder":null,"metaSortKey":-1647600609256.5,"_type":"request_group"},{"_id":"req_e002cacdd52a476fb833293359ce2407","parentId":"fld_a80d9ace53414c208c113fc52a4544f4","modified":1647614623821,"created":1647601441297,"url":"{{ _.endpoint }}/api/alerts.php","name":"Ajouter une alerte","description":"","method":"POST","body":{"mimeType":"multipart/form-data","params":[{"id":"pair_85f7cf3ba6064eac97d3c2a6666142db","name":"name","value":"Nom test","description":""},{"id":"pair_bba62ce644c1472dbdc34a10eb70824a","name":"template","value":"Température anormal : {}","description":""},{"id":"pair_9ee2741bccd741308b12d3a6a42d208c","name":"balise_id","value":"1","description":""},{"id":"pair_cb8e59303c4a4e01a44c63f7854b172f","name":"sensor_id","value":"1","description":""}]},"parameters":[],"headers":[{"name":"Content-Type","value":"multipart/form-data","id":"pair_5141d6feef0e417fb4b5ed9de5b089ab"}],"authentication":{},"metaSortKey":-1644188276092.625,"isPrivate":false,"settingStoreCookies":true,"settingSendCookies":true,"settingDisableRenderRequestBody":false,"settingEncodeUrl":true,"settingRebuildPath":true,"settingFollowRedirects":"global","_type":"request"},{"_id":"req_4468706580a548a9b8f12c8db8bfb196","parentId":"fld_a80d9ace53414c208c113fc52a4544f4","modified":1648206956910,"created":1647606353479,"url":"{{ _.endpoint }}/api/alerts.php","name":"Modifier une alerte","description":"","method":"PATCH","body":{"mimeType":"application/json","text":"{\n\t\"alert_id\":3,\n\t\"name\":\"Alerte3\",\n\t\"template\":\"Template test 3\",\n\t\"balise_id\":1,\n\t\"sensor_id\":1\n}"},"parameters":[],"headers":[{"name":"Content-Type","value":"application/json","id":"pair_5141d6feef0e417fb4b5ed9de5b089ab"}],"authentication":{},"metaSortKey":-1640775468601.25,"isPrivate":false,"settingStoreCookies":true,"settingSendCookies":true,"settingDisableRenderRequestBody":false,"settingEncodeUrl":true,"settingRebuildPath":true,"settingFollowRedirects":"global","_type":"request"},{"_id":"req_2c84b2a44e5f42ab915dfb175a394d89","parentId":"fld_a80d9ace53414c208c113fc52a4544f4","modified":1648113041849,"created":1647614596149,"url":"{{ _.endpoint }}/api/alerts.php","name":"Supprimer une alerte","description":"","method":"DELETE","body":{"mimeType":"application/json","text":"{\n\t\"alert_id\":3\n}"},"parameters":[],"headers":[{"name":"Content-Type","value":"application/json","id":"pair_5141d6feef0e417fb4b5ed9de5b089ab"}],"authentication":{},"metaSortKey":-1637362661159.875,"isPrivate":false,"settingStoreCookies":true,"settingSendCookies":true,"settingDisableRenderRequestBody":false,"settingEncodeUrl":true,"settingRebuildPath":true,"settingFollowRedirects":"global","_type":"request"},{"_id":"req_85ba01bc8e174c188f5be8511b15af81","parentId":"fld_d68fbd720a584e8e86319f65c7842117","modified":1648207800944,"created":1648207745599,"url":"{{ _.endpoint }}/api/calbr.php","name":"Lister les calibration","description":"","method":"GET","body":{},"parameters":[],"headers":[],"authentication":{},"metaSortKey":-1647601083584,"isPrivate":false,"settingStoreCookies":true,"settingSendCookies":true,"settingDisableRenderRequestBody":false,"settingEncodeUrl":true,"settingRebuildPath":true,"settingFollowRedirects":"global","_type":"request"},{"_id":"fld_d68fbd720a584e8e86319f65c7842117","parentId":"wrk_6960ae46e9804ac3853867f836617bac","modified":1648207745591,"created":1648207745591,"name":"api/calbr.php","description":"","environment":{},"environmentPropertyOrder":null,"metaSortKey":-1647600400933.75,"_type":"request_group"},{"_id":"req_421abdf4f97d4aac8017be18a6f3f1ec","parentId":"fld_d68fbd720a584e8e86319f65c7842117","modified":1648208235560,"created":1648207745595,"url":"{{ _.endpoint }}/api/calbr.php","name":"Ajouter une calibration","description":"","method":"POST","body":{"mimeType":"multipart/form-data","params":[{"id":"pair_85f7cf3ba6064eac97d3c2a6666142db","name":"balise_id","value":"1","description":""},{"id":"pair_bba62ce644c1472dbdc34a10eb70824a","name":"sensor_id","value":"1","description":""},{"id":"pair_9ee2741bccd741308b12d3a6a42d208c","name":"calbr_rect","value":"0.5","description":""}]},"parameters":[],"headers":[{"name":"Content-Type","value":"multipart/form-data","id":"pair_5141d6feef0e417fb4b5ed9de5b089ab"}],"authentication":{},"metaSortKey":-1644188276092.625,"isPrivate":false,"settingStoreCookies":true,"settingSendCookies":true,"settingDisableRenderRequestBody":false,"settingEncodeUrl":true,"settingRebuildPath":true,"settingFollowRedirects":"global","_type":"request"},{"_id":"req_9911baa8d1984ecc8a9199e2db6463d4","parentId":"fld_d68fbd720a584e8e86319f65c7842117","modified":1648207804767,"created":1648207745603,"url":"{{ _.endpoint }}/api/calbr.php","name":"Modifier une calibration","description":"","method":"PATCH","body":{"mimeType":"application/json","text":"{\n\t\"alert_id\":3,\n\t\"name\":\"Alerte3\",\n\t\"template\":\"Template test 3\",\n\t\"balise_id\":1,\n\t\"sensor_id\":1\n}"},"parameters":[],"headers":[{"name":"Content-Type","value":"application/json","id":"pair_5141d6feef0e417fb4b5ed9de5b089ab"}],"authentication":{},"metaSortKey":-1640775468601.25,"isPrivate":false,"settingStoreCookies":true,"settingSendCookies":true,"settingDisableRenderRequestBody":false,"settingEncodeUrl":true,"settingRebuildPath":true,"settingFollowRedirects":"global","_type":"request"},{"_id":"req_73020aeb5d0346e088dd8aedbf9d4606","parentId":"fld_d68fbd720a584e8e86319f65c7842117","modified":1648207806816,"created":1648207745606,"url":"{{ _.endpoint }}/api/calbr.php","name":"Supprimer une calibration","description":"","method":"DELETE","body":{"mimeType":"application/json","text":"{\n\t\"alert_id\":3\n}"},"parameters":[],"headers":[{"name":"Content-Type","value":"application/json","id":"pair_5141d6feef0e417fb4b5ed9de5b089ab"}],"authentication":{},"metaSortKey":-1637362661159.875,"isPrivate":false,"settingStoreCookies":true,"settingSendCookies":true,"settingDisableRenderRequestBody":false,"settingEncodeUrl":true,"settingRebuildPath":true,"settingFollowRedirects":"global","_type":"request"},{"_id":"req_4e188e8786be40548a566294f8c16040","parentId":"fld_06cf3816377c4685bf905a55a253e200","modified":1648715965851,"created":1646381281718,"url":"{{ _.endpoint }}/api/values.php","name":"POST","description":"","method":"POST","body":{"mimeType":"application/json","text":"{\n\t\"1\": {% randomnumber 1, 24, 0, 1 %},\n\t\"2\": {% randomnumber 1, 24, 0, 1 %},\n\t\"balise_id\": 4\n}"},"parameters":[],"headers":[{"name":"Content-Type","value":"application/json","id":"pair_f73f96730eee4133bfb22f39ead766d1","disabled":true}],"authentication":{},"metaSortKey":-1633949853718.5,"isPrivate":false,"settingStoreCookies":true,"settingSendCookies":true,"settingDisableRenderRequestBody":false,"settingEncodeUrl":true,"settingRebuildPath":true,"settingFollowRedirects":"global","_type":"request"},{"_id":"fld_06cf3816377c4685bf905a55a253e200","parentId":"wrk_6960ae46e9804ac3853867f836617bac","modified":1647600192611,"created":1647600192611,"name":"api/values.php","description":"","environment":{},"environmentPropertyOrder":null,"metaSortKey":-1647600192611,"_type":"request_group"},{"_id":"req_c9f2780788284164a430bccfa10dcdfd","parentId":"fld_06cf3816377c4685bf905a55a253e200","modified":1648714194052,"created":1648206431747,"url":"{{ _.endpoint }}/api/values.php","name":"POST_multipart","description":"","method":"POST","body":{"mimeType":"multipart/form-data","params":[{"id":"pair_8eb31a01b9fd4fe3892140515ea095a7","name":"value","value":"{% randomnumber 1, 24, 0, 1 %}","description":""},{"id":"pair_8db803fe283e4040b2f24b7fc0a83bfb","name":"balise_id","value":"1","description":""},{"id":"pair_7d64f69fdf6f455c84177956b0aa86d8","name":"sensor_id","value":"{% randomnumber 1, 2, 0, 0 %}","description":""}]},"parameters":[],"headers":[{"name":"Content-Type","value":"multipart/form-data","id":"pair_f73f96730eee4133bfb22f39ead766d1","disabled":true}],"authentication":{},"metaSortKey":-1633949853693.5,"isPrivate":false,"settingStoreCookies":true,"settingSendCookies":true,"settingDisableRenderRequestBody":false,"settingEncodeUrl":true,"settingRebuildPath":true,"settingFollowRedirects":"global","_type":"request"},{"_id":"req_3c3a04560ad348329b426b4ac3a92269","parentId":"fld_06cf3816377c4685bf905a55a253e200","modified":1647600210890,"created":1647600180620,"url":"{{ _.endpoint }}/api/values.php","name":"GET","description":"","method":"GET","body":{"mimeType":"multipart/form-data","params":[]},"parameters":[],"headers":[{"name":"Content-Type","value":"multipart/form-data","id":"pair_f73f96730eee4133bfb22f39ead766d1","disabled":true}],"authentication":{},"metaSortKey":-1633949853668.5,"isPrivate":false,"settingStoreCookies":true,"settingSendCookies":true,"settingDisableRenderRequestBody":false,"settingEncodeUrl":true,"settingRebuildPath":true,"settingFollowRedirects":"global","_type":"request"},{"_id":"req_a686b8d7e5a9408aab7f1e56f6925fc3","parentId":"fld_06cf3816377c4685bf905a55a253e200","modified":1648813141293,"created":1648119508682,"url":"{{ _.endpoint }}/api/values.php","name":"GET avec unité","description":"","method":"GET","body":{"mimeType":"multipart/form-data","params":[{"id":"pair_914380b4363c48ada27f6a36f6d781df","name":"u","value":"1","description":""},{"id":"pair_0cb6c787fcb74ca6b17381392db7a1c9","name":"","value":"","description":""}]},"parameters":[{"id":"pair_042be099b17d4a7992bcb77ec575be8e","name":"u","value":"true","description":""},{"id":"pair_8b3817acb66545f1b5314feec73c0800","name":"id","value":"1","description":""}],"headers":[{"name":"Content-Type","value":"multipart/form-data","id":"pair_646d3f47726249b0be4494186e27fd12"}],"authentication":{},"metaSortKey":-1633949853618.5,"isPrivate":false,"settingStoreCookies":true,"settingSendCookies":true,"settingDisableRenderRequestBody":false,"settingEncodeUrl":true,"settingRebuildPath":true,"settingFollowRedirects":"global","_type":"request"},{"_id":"env_79c810119d68db74c817f1dcca7136cf39927876","parentId":"wrk_6960ae46e9804ac3853867f836617bac","modified":1647002699301,"created":1646381270611,"name":"Base Environment","data":{"endpoint":"http://127.0.0.1/edsa-pesquiers"},"dataPropertyOrder":{"&":["endpoint"]},"color":null,"isPrivate":false,"metaSortKey":1646381270611,"_type":"environment"},{"_id":"jar_79c810119d68db74c817f1dcca7136cf39927876","parentId":"wrk_6960ae46e9804ac3853867f836617bac","modified":1646381270617,"created":1646381270617,"name":"Default Jar","cookies":[],"_type":"cookie_jar"},{"_id":"spc_052f751b9b0f4fecb1ec133d4e98acb6","parentId":"wrk_6960ae46e9804ac3853867f836617bac","modified":1646381270596,"created":1646381270596,"fileName":"Monitoring Pesquiers","contents":"","contentType":"yaml","_type":"api_spec"}]}